<WndTap Name="prj_agreement_line_v" Text="prj_agreement_line">
<WndTaps>
<xi:include xmlns:xi="http://www.w3.org/2001/XInclude" href="prj_agreement_line_Ve.xml" popup="1"/>
</WndTaps>
<xi:include xmlns:xi="http://www.w3.org/2001/XInclude" href="lan\prj_agreement_line.xml"/>
<Ctrls><GroupBox  Name="GBprj_agreement_line" id="prj_agreement_line" Text="prj_agreement_line" Size="100,100"><Ctrls>
<xi:include xmlns:xi="http://www.w3.org/2001/XInclude" href="prj_agreement_line_Vvm.xml"/>
</Ctrls></GroupBox>
</Ctrls></WndTap>
