<GroupBox Name="GBDEDIThr_leave_entitlement_header" text="Search" toggle="1"><Ctrls>
<GroupBox Name="GB_entitlement_name" Multiline="0" cols="xs12 sm6 md4"><Ctrls>
<Label Name="lb_entitlement_name" Size="60,20" Text="entitlement_name" Align="Right"/>
<TextBox Name="entitlement_name" Size="170,20" Text="" Weight="170" ToolTip="ttp_entitlement_name"></TextBox>
</Ctrls></GroupBox>
<GroupBox Name="GB_leave_group" Multiline="0" cols="xs12 sm6 md4"><Ctrls>
<Label Name="lb_leave_group" Size="60,20" Text="leave_group" Align="Right"/>
<TextBox Name="leave_group" Size="170,20" Text="" Weight="170" ToolTip="ttp_leave_group"></TextBox>
</Ctrls></GroupBox>
<GroupBox Name="GB_status" Multiline="0" cols="xs12 sm6 md4"><Ctrls>
<Label Name="lb_status" Size="60,20" Text="status" Align="Right"/>
<TextBox Name="status" Size="170,20" Text="" Weight="170" ToolTip="ttp_status"></TextBox>
</Ctrls></GroupBox>
</Ctrls></GroupBox>